rfdevices/__init__.py
rfdevices/_version.py
rfdevices/config.py
rfdevices/const.py
rfdevices/device.py
rfdevices/protocol.py
rfdevices/transmitter.py
rfdevices/protocols/harbor-breeze.conf
rfdevices/protocols/rcswitch.conf
rfdevices-0.3.0.data/scripts/rfsend
rfdevices-0.3.0.dist-info/DESCRIPTION.rst
rfdevices-0.3.0.dist-info/METADATA
rfdevices-0.3.0.dist-info/RECORD
rfdevices-0.3.0.dist-info/WHEEL
rfdevices-0.3.0.dist-info/metadata.json
rfdevices-0.3.0.dist-info/top_level.txt
