Metadata-Version: 2.0
Name: rfdevices
Version: 0.3.0
Summary: Control household RF devices with low-cost GPIO modules
Home-page: https://github.com/milas/rfdevices
Author: Milas Bowman
Author-email: milasb@gmail.com
License: BSD
Keywords: rpi,raspberry,raspberry pi,adafruit,beaglebone,rf,gpio,radio,433,433mhz,315,315mhz
Platform: UNKNOWN
Classifier: Development Status :: 4 - Beta
Classifier: Intended Audience :: Developers
Classifier: Topic :: Software Development
Classifier: Topic :: Home Automation
Classifier: Topic :: System :: Hardware
Classifier: Topic :: Software Development :: Libraries :: Python Modules
Classifier: License :: OSI Approved :: BSD License
Classifier: Programming Language :: Python :: 3
Classifier: Operating System :: POSIX :: Linux
Requires-Dist: Adafruit-GPIO
